<?xml version="1.0" encoding="UTF-8"?><database>
    <element db_object_id="180bd15d93440210abc23aaefaba104f" label="Skill" max_length="40" name="x_1282466_skill_0_se_skill" text_index="true" type="collection">
        <element attributes="ignore_filter_on_new=true" default="javascript:global.getNextObjNumberPadded();" label="Number" max_length="40" name="number" type="string"/>
        <element label="Product line" max_length="32" name="product_line" reference="x_1282466_skill_0_se_product_line" type="reference"/>
        <element label="Skill description" max_length="256" name="skill_description" type="string"/>
        <element default="javascript:current.getTableName();" label="Class" max_length="80" name="sys_class_name" type="sys_class_name"/>
        <element label="Weight" max_length="40" name="weight" type="integer"/>
        <index name="index">
            <element name="product_line"/>
        </index>
        <index name="index2">
            <element name="sys_class_name"/>
        </index>
    </element>
</database>
